streamlit_pinecone/__init__.py
streamlit_pinecone/pinecone_conn.py
streamlit_pinecone-1.0.0.dist-info/LICENSE
streamlit_pinecone-1.0.0.dist-info/METADATA
streamlit_pinecone-1.0.0.dist-info/WHEEL
streamlit_pinecone-1.0.0.dist-info/top_level.txt
streamlit_pinecone-1.0.0.dist-info/RECORD
