Metadata-Version: 2.1
Name: streamlit-pinecone
Version: 1.0.0
Summary: A Streamlit extension for connecting to Pinecone indexes.
Author-email: Eliot Lee <eliotlee2026@u.northwestern.edu>
License: MIT License
Project-URL: Homepage, https://github.com/eliotjlee/streamlit-pinecone
Keywords: streamlit,pinecone,data connection,vector database,streamlit component
Classifier: License :: OSI Approved :: MIT License
Classifier: Programming Language :: Python
Classifier: Programming Language :: Python :: 3
Classifier: Programming Language :: Python :: 3.9
Requires-Python: >=3.9
License-File: LICENSE
Requires-Dist: streamlit >=1.28
Requires-Dist: pinecone-client >=2.2.2
